protexam/__init__.py
protexam/__main__.py
protexam/app.py
protexam/config.ini
protexam/config.json
protexam/helpers.py
protexam-0.9.1.dist-info/LICENSE
protexam-0.9.1.dist-info/METADATA
protexam-0.9.1.dist-info/WHEEL
protexam-0.9.1.dist-info/top_level.txt
protexam-0.9.1.dist-info/RECORD
