Metadata-Version: 2.1
Name: protexam
Version: 0.9.1
Summary: Inspect your quantitative proteomics results using this streamlit-powered dashboard. The app is specifically tailored for comprehensive examination of result files from isobaric labeling-based quantitative experiments.
Home-page: https://github.com/dev-ev/protexam
Author: Proteome Proteomicsson 101
Author-email: proteomicsson@gmail.com
License: BSD
Keywords: proteomics mass-spectrometry visualization streamlit
Platform: UNKNOWN
Classifier: Development Status :: 4 - Beta
Classifier: Topic :: Scientific/Engineering :: Bio-Informatics
Classifier: Topic :: Scientific/Engineering :: Visualization
Classifier: License :: OSI Approved :: BSD License
Requires-Dist: bokeh (<=2.4.1)
Requires-Dist: matplotlib (<4.0)
Requires-Dist: numpy
Requires-Dist: pandas
Requires-Dist: scikit-learn
Requires-Dist: scipy
Requires-Dist: seaborn (<1.0)
Requires-Dist: streamlit (>=1.0)
